rag_eval_tool/__init__.py
rag_eval_tool/rag_eval_tool.py
rag_eval_tool-0.1.9.dist-info/METADATA
rag_eval_tool-0.1.9.dist-info/WHEEL
rag_eval_tool-0.1.9.dist-info/top_level.txt
rag_eval_tool-0.1.9.dist-info/RECORD
