Metadata-Version: 2.1
Name: rag_eval_tool
Version: 0.1.9
Summary: A comprehensive evaluation toolkit for RAG and LLMs.
Author: Pratik Bhande
Author-email: pratikbhande2@gmail.com
Classifier: Programming Language :: Python :: 3
Classifier: License :: OSI Approved :: MIT License
Classifier: Operating System :: OS Independent
Requires-Python: >=3.7
Requires-Dist: torch
Requires-Dist: sacrebleu
Requires-Dist: rouge-score
Requires-Dist: bert-score
Requires-Dist: transformers
Requires-Dist: nltk
Requires-Dist: textstat
Requires-Dist: scikit-learn
Requires-Dist: numpy
Requires-Dist: protobuf
Requires-Dist: tqdm
